{
  "text": "Vou buscar no X o perfil oficial da UNDIME Rondônia, sem usar ferramentas locais de arquivo.\n",
  "stopReason": "Cancelled",
  "sessionId": "019ef037-90db-7bc3-9af3-e88549257688",
  "requestId": "3fe0f2ae-8c22-48a9-9437-f61e71e3534c",
  "thought": "The user is asking me to search for an official UNDIME Rondônia profile on X (Twitter) without using local file tools. They want me to use X search capabilities. Based on the project rules, there's mention of `grok.exe` local authenticated for X.\n"
}
